tests
yati
