Metadata-Version: 1.0
Name: yati
Version: 1.0.0
Summary: Yet Another Twitter Interface: A Twitter CLI
Home-page: https://github.com/traviskaufman/YATI
Author: Travis Kaufman
Author-email: travis.kaufman@gmail.com
License: GPL
Download-URL: http://pypi.python.org/packages/source/y/yati/yati-1.0.0dev.tar.gz
Platform: UNKNOWN
